{"cameraMode":{"drawMode":0,"name":"Shaded","section":"Shading Mode"},"sceneLighting":true,"audioPlay":false,"sceneViewState":{"showFog":true,"showMaterialUpdate":false,"showSkybox":true,"showFlares":true,"showImageEffects":true,"showParticleSystems":true},"in2DMode":false,"pivot":{"x":978.4024658203125,"y":317.8067321777344,"z":-2.075592041015625},"rotation":{"x":-0.03656558692455292,"y":-0.0434093177318573,"z":-0.0015850466443225742,"w":0.9985153675079346},"size":344.33404541015627,"orthographic":false}